odoo/addons/website_sale_stock_picking_note/README.rst
odoo/addons/website_sale_stock_picking_note/__init__.py
odoo/addons/website_sale_stock_picking_note/__manifest__.py
odoo/addons/website_sale_stock_picking_note/controllers/__init__.py
odoo/addons/website_sale_stock_picking_note/controllers/main.py
odoo/addons/website_sale_stock_picking_note/data/data.xml
odoo/addons/website_sale_stock_picking_note/i18n/ca.po
odoo/addons/website_sale_stock_picking_note/i18n/es.po
odoo/addons/website_sale_stock_picking_note/i18n/fr.po
odoo/addons/website_sale_stock_picking_note/i18n/website_sale_stock_picking_note.pot
odoo/addons/website_sale_stock_picking_note/models/__init__.py
odoo/addons/website_sale_stock_picking_note/models/customer_comment_config.py
odoo/addons/website_sale_stock_picking_note/readme/CONFIGURE.rst
odoo/addons/website_sale_stock_picking_note/readme/CONTRIBUTORS.rst
odoo/addons/website_sale_stock_picking_note/readme/DESCRIPTION.rst
odoo/addons/website_sale_stock_picking_note/readme/USAGE.rst
odoo/addons/website_sale_stock_picking_note/static/description/icon.png
odoo/addons/website_sale_stock_picking_note/static/description/index.html
odoo/addons/website_sale_stock_picking_note/static/src/js/website_sale_stock_picking_note.js
odoo/addons/website_sale_stock_picking_note/views/assets.xml
odoo/addons/website_sale_stock_picking_note/views/customer_comment_config_view.xml
odoo/addons/website_sale_stock_picking_note/views/template.xml
odoo12_addon_website_sale_stock_picking_note-12.0.1.0.0.99.dev8.dist-info/METADATA
odoo12_addon_website_sale_stock_picking_note-12.0.1.0.0.99.dev8.dist-info/WHEEL
odoo12_addon_website_sale_stock_picking_note-12.0.1.0.0.99.dev8.dist-info/top_level.txt
odoo12_addon_website_sale_stock_picking_note-12.0.1.0.0.99.dev8.dist-info/RECORD
